kpx/__init__.py
kpx/aws_acm.py
kpx/aws_config.py
kpx/aws_ec2.py
kpx/aws_ecr.py
kpx/aws_lb.py
kpx/aws_route53.py
kpx/aws_vpc.py
kpx/k8s.py
kpx/main.py
kpx/utils.py
kpx-0.9.0.dist-info/METADATA
kpx-0.9.0.dist-info/WHEEL
kpx-0.9.0.dist-info/entry_points.txt
kpx-0.9.0.dist-info/RECORD
