Metadata-Version: 2.3
Name: kpx
Version: 0.9.0
Summary: CLI tool for AWS configuration files and quick interogations to AWS API
License: APACHE 2
Author: BogdanR
Author-email: 367815-marius-rizac@users.noreply.gitlab.com
Requires-Python: >=3.9,<4.0
Classifier: License :: Other/Proprietary License
Classifier: Programming Language :: Python :: 3
Classifier: Programming Language :: Python :: 3.9
Classifier: Programming Language :: Python :: 3.10
Classifier: Programming Language :: Python :: 3.11
Classifier: Programming Language :: Python :: 3.12
Classifier: Programming Language :: Python :: 3.13
Requires-Dist: boto3 (>=1.35.97,<2.0.0)
Requires-Dist: kubernetes (>=30.1.0,<31.0.0)
Requires-Dist: prettytable (>=3.10.2,<4.0.0)
Requires-Dist: typer (>=0.12.3,<0.13.0)
